{"cameraMode":{"drawMode":0,"name":"Shaded","section":"Shading Mode"},"sceneLighting":false,"audioPlay":false,"sceneViewState":{"m_AlwaysRefresh":false,"showFog":true,"showSkybox":false,"showFlares":false,"showImageEffects":false,"showParticleSystems":false,"showVisualEffectGraphs":false,"m_FxEnabled":true},"in2DMode":false,"pivot":{"x":0.0,"y":0.0,"z":5.960464477539063e-8},"rotation":{"x":0.23127572238445283,"y":-0.049012139439582828,"z":-0.011666926555335522,"w":-0.9715867042541504},"size":0.4522438645362854,"orthographic":false}